cinplus/__init__.py
cinplus-1.0.1.dist-info/LICENSE
cinplus-1.0.1.dist-info/METADATA
cinplus-1.0.1.dist-info/WHEEL
cinplus-1.0.1.dist-info/top_level.txt
cinplus-1.0.1.dist-info/RECORD
