Metadata-Version: 2.1
Name: cinplus
Version: 1.0.1
Summary: A Python module that extends the basic input function with 16 different parameters and many combinations.
Home-page: https://github.com/woskethebot/cinplus
Author: woskethebot
Author-email: nushratakhter1999@gmail.com
Classifier: Programming Language :: Python :: 3
Classifier: License :: OSI Approved :: Mozilla Public License 2.0 (MPL 2.0)
Classifier: Operating System :: Microsoft :: Windows
Requires-Python: >=3.6
License-File: LICENSE
